flynt/__init__.py
flynt/__main__.py
flynt/_git_version.py
flynt/api.py
flynt/cli.py
flynt/code_editor.py
flynt/exceptions.py
flynt/state.py
flynt/candidates/__init__.py
flynt/candidates/ast_call_candidates.py
flynt/candidates/ast_chunk.py
flynt/candidates/ast_percent_candidates.py
flynt/linting/__init__.py
flynt/linting/fstr_lint.py
flynt/static_join/__init__.py
flynt/static_join/candidates.py
flynt/static_join/transformer.py
flynt/static_join/utils.py
flynt/string_concat/__init__.py
flynt/string_concat/candidates.py
flynt/string_concat/string_in_string.py
flynt/string_concat/transformer.py
flynt/transform/FstringifyTransformer.py
flynt/transform/__init__.py
flynt/transform/format_call_transforms.py
flynt/transform/percent_transformer.py
flynt/transform/transform.py
flynt/transform/util.py
flynt/utils/__init__.py
flynt/utils/format.py
flynt/utils/pyproject_finder.py
flynt/utils/utils.py
flynt-1.0.6.dist-info/METADATA
flynt-1.0.6.dist-info/WHEEL
flynt-1.0.6.dist-info/entry_points.txt
flynt-1.0.6.dist-info/licenses/LICENSE
flynt-1.0.6.dist-info/RECORD
