Metadata-Version: 2.4
Name: flynt
Version: 1.0.6
Summary: CLI tool to convert a python project's %-formatted strings to f-strings.
Project-URL: Homepage, https://github.com/ikamensh/flynt
Author: Ilya Kamenshchikov
License: MIT
License-File: LICENSE
Keywords: strings,utility
Classifier: Programming Language :: Python
Classifier: Programming Language :: Python :: 3
Classifier: Programming Language :: Python :: 3.9
Classifier: Programming Language :: Python :: 3.10
Classifier: Programming Language :: Python :: 3.11
Classifier: Programming Language :: Python :: 3.12
Classifier: Programming Language :: Python :: 3.13
Classifier: Topic :: Software Development :: Libraries :: Python Modules
Classifier: Topic :: Utilities
Requires-Python: >=3.9
Requires-Dist: tomli>=1.1.0; python_version < '3.11'
Provides-Extra: dev
Requires-Dist: build; extra == 'dev'
Requires-Dist: pre-commit; extra == 'dev'
Requires-Dist: pytest; extra == 'dev'
Requires-Dist: pytest-cov; extra == 'dev'
Requires-Dist: ruff; extra == 'dev'
Requires-Dist: twine; extra == 'dev'
